conf_finder/__init__.py
conf_finder/__version__.py
conf_finder/conf_finder.py
conf_finder/py.typed
conf_finder-0.3.1.dist-info/METADATA
conf_finder-0.3.1.dist-info/WHEEL
conf_finder-0.3.1.dist-info/licenses/LICENSE
conf_finder-0.3.1.dist-info/RECORD
