Metadata-Version: 2.4
Name: conf-finder
Version: 0.3.1
Summary: Configuration file finder.
Project-URL: Repository, https://github.com/rcmdnk/conf-finder
Project-URL: Homepage, https://github.com/rcmdnk/conf-finder
Author-email: rcmdnk <rcmdnk@gmail.com>
License-Expression: Apache-2.0
License-File: LICENSE
Keywords: CONFIG,Git,XGB,XGB_CONFIG_HOME
Requires-Python: >=3.9
Requires-Dist: gitpython>=3.1.41
Requires-Dist: pyaml>=24.12.1
Requires-Dist: tomli>=2.0.1; python_version < '3.11'
